Workbook

Sheet Project Dashboard
A1: Water Damage Restoration & Rebuild Project
A2: Illustrative Flowshua portfolio case study | Fictional project data only
A5: Overall Project Completion | C5: Schedule Health | E5: Budget Used | G5: Open Control Items | I5: Final Walkthrough Forecast | K5: Quality Gate Readiness
A6: =SUM('Work Packages'!$K$6:$K$20)/SUM('Work Packages'!$H$6:$H$20) -> 0.373 | C6: =IF(COUNTIF('Master Schedule'!$G$6:$G$20,"At Risk")>0,"At Risk","On Track") -> At Risk | E6: =SUM('Budget & Forecast'!$C$11:$C$16)/SUM('Budget & Forecast'!$B$11:$B$16) -> 0.37714286 | G6: =COUNTIF(RAIDD!$H$6:$H$15,"Open")+COUNTIF(RAIDD!$H$6:$H$15,"At Risk") -> 8 | I6: ="Week "&MAX('Quality Gates'!$F$6:$F$12) -> Week 12 | K6: =COUNTIF('Quality Gates'!$G$6:$G$12,"Complete")&" of 7" -> 1 of 7
A7: Weighted project progress | C7: Critical project steps are being watched | E7: Actual and committed cost to date | G7: Risks, issues, and dependencies | I7: Target owner walkthrough window | K7: Quality gates completed
A10: Project Objective | G10: Portfolio Boundary
A11: Return a fictional water-damaged home to a safe, livable, and homeowner-approved condition within a 12-week rebuild window while keeping scope, vendors, materials, inspections, and communication organized. | G11: This portfolio case study uses fictional home details, trade work, dates, budget values, and homeowner information. It shows project setup and coordination methods. It does not provide construction advice, insurance claim advice, or contractor work.
A17: Management Focus | G17: Critical Path View
A18: Focus | B18: Current Signal | C18: Owner | D18: Why It Matters | E18: Next Action | F18: Status | G18: Phase | H18: Planned Window | I18: Forecast Window | J18: Primary Dependency | K18: Health | L18: Control Note
A19: Scope and insurance approval | B19: Initial damage scope is documented, but one hidden moisture item still needs approval. | C19: Project Lead | D19: Stops us from starting work that is not covered or fully understood. | E19: Send photos and scope add-on to the adjuster. | F19: In Progress | G19: Assessment & scope | H19: Weeks 1-2 | I19: Weeks 1-2 | J19: Moisture inspection and adjuster response | K19: In Progress | L19: Keep every scope change in one log.
A20: Long-lead materials | B20: Cabinet and flooring choices can affect the finish dates. | C20: Project Lead | D20: Could push cabinets, trim, flooring, and the final walkthrough. | E20: Lock homeowner selections and confirm delivery dates. | F20: At Risk | G20: Materials & vendor planning | H20: Weeks 2-4 | I20: Weeks 2-4 | J20: Homeowner selections and vendor lead times | K20: At Risk | L20: Check material dates twice a week.
A21: Critical path | B21: Plumbing, electrical, drywall, and finish work have to stay in order. | C21: Reconstruction Lead | D21: One missed handoff can make the next trade wait. | E21: Confirm the next trade before current work closes out. | F21: In Progress | G21: Reconstruction | H21: Weeks 3-8 | I21: Weeks 3-8 | J21: Trade handoffs and inspection windows | K21: In Progress | L21: Protect the rough-in and drywall sequence.
A22: Final quality | B22: Final walkthrough criteria are being built before the job reaches the end. | C22: Project Lead | D22: Avoids a long punch list after the homeowner thinks the job is done. | E22: Use a room-by-room checklist before the owner walkthrough. | F22: In Progress | G22: Finishes & inspection | H22: Weeks 8-11 | I22: Weeks 8-11 | J22: Material arrivals and trade completion | K22: Watch | L22: Keep homeowner expectations visible.
A23: Closeout preparation | B23: Warranty and closeout paperwork starts before the final walk. | C23: Project Lead | D23: Keeps loose ends from dragging after the home is ready. | E23: Draft the warranty packet and final project summary. | F23: Not Started | G23: Final walk & closeout | H23: Weeks 11-12 | I23: Weeks 11-12 | J23: Punch list and homeowner availability | K23: Not Started | L23: Closeout package needs to be ready before final walk.
A26: Work Package Status Mix | E26: Workbook Map
A27: Status | B27: Count | E27: Sheet | F27: Purpose
A28: Complete | B28: =COUNTIF('Work Packages'!$I$6:$I$20,"Complete") -> 3 | E28: Project Charter | F28: Project purpose, scope, homeowner and vendor roles, and portfolio boundaries.
A29: In Progress | B29: =COUNTIF('Work Packages'!$I$6:$I$20,"In Progress") -> 4 | E29: Work Packages | F29: Detailed rebuild work packages with ownership, progress, dependencies, and schedule impact.
A30: At Risk | B30: =COUNTIF('Work Packages'!$I$6:$I$20,"At Risk") -> 2 | E30: Master Schedule | F30: 12-week home rebuild plan with a visual Gantt-style timeline.
A31: Not Started | B31: =COUNTIF('Work Packages'!$I$6:$I$20,"Not Started") -> 6 | E31: Budget & Forecast | F31: Baseline, actual and committed cost, forecast, variance, and project cost view.
E32: Procurement & Dependencies | F32: Materials, vendor dates, inspections, and dependencies tied to the rebuild.
A33: Budget Snapshot | E33: Quality Gates | F33: Approval, inspection, walkthrough, and closeout checkpoints.
A34: Metric | B34: Value | E34: RAIDD | F34: Risks, assumptions, issues, decisions, and dependencies that need a clear owner.
A35: Baseline Budget | B35: =SUM('Budget & Forecast'!$B$11:$B$16) -> 175000 | E35: Lessons Learned | F35: Reusable project coordination lessons and closeout checklist.
A36: Actual / Committed | B36: =SUM('Budget & Forecast'!$C$11:$C$16) -> 66000 | E36: Project Dashboard | F36: Executive view for weekly owner, vendor, and project updates.
A37: Forecast at Completion | B37: =SUM('Budget & Forecast'!$D$11:$D$16) -> 179000
A38: Forecast Remaining | B38: =B37-B36 -> 113000
A42: Flowshua Projects | Clearer projects. Stronger follow-through.

Sheet Project Charter
A1: Project Charter
A2: Water Damage Restoration & Rebuild Project | Fictional portfolio case study
A5: Project Summary
A6: Project Name | B6: Water Damage Restoration & Rebuild Project | D6: Objective | E6: Return a fictional home to a safe, livable, and homeowner-approved condition after a pipe burst causes water damage while the owners are out of town. Keep the scope, vendors, schedule, decisions, and final walk organized.
A7: Project Type | B7: Illustrative home restoration and rebuild case study | D7: Business Need | E7: Get a damaged home rebuilt without losing track of insurance approvals, trade handoffs, materials, homeowner decisions, or closeout items.
A8: Project Sponsor | B8: Homeowner / Property Owner (fictional role) | D8: Primary Constraint | E8: Insurance approval, hidden damage, material lead times, and trade availability drive the critical path.
A9: Project Coordinator | B9: Project Coordinator (portfolio scenario) | D9: Operating Assumption | E9: Emergency mitigation is complete, but the home stays out of normal use until work, inspections, and final walkthrough are complete.
A10: Planned Duration | B10: 12 weeks | D10: Success Measure | E10: Home is safe, complete, and ready for owner walkthrough by Week 12 without losing control of cost, quality, or homeowner communication.
A11: Baseline Budget | B11: $175,000 | D11: Portfolio Boundary | E11: All data is fictional. This case study does not reproduce a real home, insurance claim, customer information, contractor proposal, or repair estimate.
A12: Target Outcome | B12: Homeowner-approved rebuild and project closeout | D12: Project Approach | E12: Clear project setup, visible ownership, early risk escalation, trade coordination, and disciplined closeout.
A15: In Scope | G15: Out of Scope
A16: Included work | B16: Initial damage review and rebuild plan | G16: Excluded item | H16: Licensed construction work or contractor management
A17: Included work | B17: Fictional material planning, vendor tracking, and trade sequencing | G17: Excluded item | H17: Insurance claim negotiation or coverage decisions
A18: Included work | B18: Homeowner update process, quality gates, and final walkthrough checklist | G18: Excluded item | H18: Real customer, home, vendor, or restoration company information
A19: Included work | B19: Project budget, schedule, risk controls, and lessons learned | G19: Excluded item | H19: Construction drawings, building code advice, or repair instructions
A20: Included work | B20: Weekly project updates and owner visibility | G20: Excluded item | H20: Any claim that this workbook represents a real client project
A23: Stakeholder & Governance Map
A24: Stakeholder / Role | B24: Project Interest | C24: Decision Rights | D24: Cadence | E24: Key Input | G24: Stakeholder / Role | H24: Project Interest | I24: Decision Rights | J24: Cadence | K24: Key Input
A25: Homeowner / Property Owner | B25: Safe return to a usable home | C25: Approves major choices and final walkthrough | D25: Weekly project update | E25: Scope decisions and finish selections | G25: Project Coordinator | H25: Integrated project control | I25: Coordinates changes and escalations | J25: Daily control review | K25: Scope, schedule, cost, and risk visibility
A26: Project Coordinator | B26: Keeps the plan, updates, risks, and next steps clear | C26: Coordinates updates and escalations | D26: Daily control review | E26: Scope, schedule, cost, and risk visibility | G26: Restoration Lead | H26: Field work and vendor coordination | I26: Forecasts work package completion | J26: Daily rebuild update | K26: Trade sequence, vendor status, and site access
A27: Restoration Lead | B27: Field work and trade sequence | C27: Confirms field readiness and trade handoffs | D27: Daily job check | E27: Field progress, access, and work completion | G27: Materials / Supplier Lead | H27: Cabinets, flooring, trim, and key materials | I27: Confirms delivery dates and substitutions | J27: Twice-weekly vendor review | K27: Lead times, alternates, and delivery confidence
A28: Quality / Inspection Lead | B28: Safe, complete, and documented finish | C28: Signs off quality gates | D28: Gate-driven | E28: Inspection timing and final punch list | G28: Homeowner Liaison | H28: Clear homeowner communication | I28: Coordinates decision requests and updates | J28: Weekly or as needed | K28: Finish choices, concerns, and access needs
A29: Vendor / Trade Lead | B29: Trade availability and delivery dates | C29: Provides work windows and completion updates | D29: As needed | E29: Labor, material, and access constraints | G29: Boundary Statement | H29: Fictional portfolio prototype | I29: No external authority | J29: Always visible | K29: Uses non-sensitive, illustrative data only
A30: Flowshua Projects | Clearer projects. Stronger follow-through.

Sheet Work Packages
A1: Work Package Register
A2: Detailed scope, ownership, progress, dependency, and schedule-control view | Fictional project data only
A5: Work Package ID | B5: Phase | C5: Work Package | D5: Owner | E5: Duration Days | F5: Start Week | G5: Finish Week | H5: Weight | I5: Status | J5: Percent Complete | K5: Earned Progress | L5: Primary Dependency | M5: Schedule Impact | N5: Control Note
A6: WP-001 | B6: Initiation | C6: Complete mitigation handoff and organize damage records | D6: Restoration Lead | E6: 5 | F6: 1 | G6: 1 | H6: 0.05 | I6: Complete | J6: 1 | K6: =H6*J6 -> 0.05 | L6: Project kickoff | M6: Low | N6: Drying records, photos, and initial scope are in the project file.
A7: WP-002 | B7: Initiation | C7: Confirm the approved rebuild scope and insurance decisions | D7: Project Lead | E7: 5 | F7: 1 | G7: 2 | H7: 0.06 | I7: In Progress | J7: 0.75 | K7: =H7*J7 -> 0.045 | L7: WP-001 | M7: Medium | N7: One concealed moisture item is still waiting on approval.
A8: WP-003 | B8: Planning | C8: Build the rebuild plan, vendor tracker, and homeowner update plan | D8: Project Coordinator | E8: 5 | F8: 1 | G8: 2 | H8: 0.07 | I8: Complete | J8: 1 | K8: =H8*J8 -> 0.07 | L8: WP-001 | M8: Low | N8: One tracker and update format are ready for the project.
A9: WP-004 | B9: Planning | C9: Lock in cabinet, flooring, trim, and material lead times | D9: Materials Lead | E9: 7 | F9: 2 | G9: 3 | H9: 0.07 | I9: At Risk | J9: 0.4 | K9: =H9*J9 -> 0.028 | L9: WP-003 | M9: High | N9: Cabinet and flooring delivery dates drive the finish schedule.
A10: WP-005 | B10: Planning | C10: Confirm trade sequence, site access plan, and work windows | D10: Reconstruction Lead | E10: 6 | F10: 2 | G10: 3 | H10: 0.07 | I10: Complete | J10: 1 | K10: =H10*J10 -> 0.07 | L10: WP-003 | M10: Low | N10: Trade handoffs and access needs are documented.
A11: WP-006 | B11: Execution | C11: Finish demo, dry-out verification, plumbing, and structural repairs | D11: Restoration Lead | E11: 18 | F11: 3 | G11: 6 | H11: 0.1 | I11: In Progress | J11: 0.5 | K11: =H11*J11 -> 0.05 | L11: WP-005 | M11: Medium | N11: Protect the repair window and keep hidden damage visible.
A12: WP-007 | B12: Execution | C12: Complete electrical, plumbing, and inspection signoffs before walls close | D12: Trade Leads | E12: 12 | F12: 4 | G12: 6 | H12: 0.08 | I12: At Risk | J12: 0.3 | K12: =H12*J12 -> 0.024 | L12: WP-006 | M12: High | N12: Inspection availability and rough-in completion drive drywall start.
A13: WP-008 | B13: Execution | C13: Complete drywall, texture, paint, and ceiling repairs | D13: Finish Lead | E13: 14 | F13: 6 | G13: 8 | H13: 0.1 | I13: In Progress | J13: 0.1 | K13: =H13*J13 -> 0.01 | L13: WP-007 | M13: Medium | N13: Do not start until rough-in work and inspection needs are clear.
A14: WP-009 | B14: Integration | C14: Install cabinets, trim, and finish carpentry | D14: Finish Lead | E14: 15 | F14: 8 | G14: 10 | H14: 0.1 | I14: Not Started | J14: 0 | K14: =H14*J14 -> 0 | L14: WP-004 | M14: High | N14: Start only when cabinets arrive and paint work is complete.
A15: WP-010 | B15: Integration | C15: Install flooring, fixtures, and appliances | D15: Finish Lead | E15: 10 | F15: 9 | G15: 10 | H15: 0.07 | I15: Not Started | J15: 0 | K15: =H15*J15 -> 0 | L15: WP-009 | M15: High | N15: Flooring availability and cabinet completion drive this step.
A16: WP-011 | B16: Quality | C16: Complete room-by-room quality walkthrough and create punch list | D16: Project Coordinator | E16: 5 | F16: 10 | G16: 11 | H16: 0.05 | I16: Not Started | J16: 0 | K16: =H16*J16 -> 0 | L16: WP-010 | M16: High | N16: Use photos, room list, and homeowner priorities before final walk.
A17: WP-012 | B17: Quality | C17: Close punch list, complete final cleaning, and build warranty packet | D17: Restoration Lead | E17: 5 | F17: 11 | G17: 11 | H17: 0.05 | I17: Not Started | J17: 0 | K17: =H17*J17 -> 0 | L17: WP-011 | M17: Medium | N17: Do not let final cleaning happen before all trade work is done.
... A20: WP-015 | B20: Closeout | C20: Capture lessons learned and archive the project file | D20: Project Coordinator | E20: 3 | F20: 12 | G20: 12 | H20: 0.04 | I20: Not Started | J20: 0 | K20: =H20*J20 -> 0 | L20: WP-013 | M20: Medium | N20: Archive the final tracker, updates, warranties, and closeout notes.
A21: Flowshua Projects | Clearer projects. Stronger follow-through.

Sheet Master Schedule
A1: Master Schedule & Rebuild Plan
A2: 12-week rebuild plan with critical-path visibility | Fictional project data only
A5: Phase | B5: Milestone / Deliverable | C5: Owner | D5: Start Week | E5: Finish Week | F5: Duration Days | G5: Health | H5: 1 | I5: 2 | J5: 3 | K5: 4 | L5: 5 | M5: 6 | N5: 7 | O5: 8 | P5: 9 | Q5: 10 | R5: 11 | S5: 12
A6: Initiation | B6: Mitigation handoff and damage record complete | C6: Restoration Lead | D6: 1 | E6: 1 | F6: 5 | G6: Complete | H6: =IF(AND(H$5>=$D6,H$5<=$E6),"●","") -> ● | I6: =IF(AND(I$5>=$D6,I$5<=$E6),"●","") | J6: =IF(AND(J$5>=$D6,J$5<=$E6),"●","") | K6: =IF(AND(K$5>=$D6,K$5<=$E6),"●","") | L6: =IF(AND(L$5>=$D6,L$5<=$E6),"●","") | M6: =IF(AND(M$5>=$D6,M$5<=$E6),"●","") | N6: =IF(AND(N$5>=$D6,N$5<=$E6),"●","") | O6: =IF(AND(O$5>=$D6,O$5<=$E6),"●","") | ... S6: =IF(AND(S$5>=$D6,S$5<=$E6),"●","")
A7: Initiation | B7: Project charter and rebuild goal approved | C7: Homeowner / Project Lead | D7: 1 | E7: 1 | F7: 3 | G7: Complete | H7: =IF(AND(H$5>=$D7,H$5<=$E7),"●","") -> ● | I7: =IF(AND(I$5>=$D7,I$5<=$E7),"●","") | J7: =IF(AND(J$5>=$D7,J$5<=$E7),"●","") | K7: =IF(AND(K$5>=$D7,K$5<=$E7),"●","") | L7: =IF(AND(L$5>=$D7,L$5<=$E7),"●","") | M7: =IF(AND(M$5>=$D7,M$5<=$E7),"●","") | N7: =IF(AND(N$5>=$D7,N$5<=$E7),"●","") | O7: =IF(AND(O$5>=$D7,O$5<=$E7),"●","") | ... S7: =IF(AND(S$5>=$D7,S$5<=$E7),"●","")
A8: Planning | B8: Rebuild plan, vendor tracker, and homeowner update plan ready | C8: Project Coordinator | D8: 1 | E8: 2 | F8: 5 | G8: Complete | H8: =IF(AND(H$5>=$D8,H$5<=$E8),"●","") -> ● | I8: =IF(AND(I$5>=$D8,I$5<=$E8),"●","") -> ● | J8: =IF(AND(J$5>=$D8,J$5<=$E8),"●","") | K8: =IF(AND(K$5>=$D8,K$5<=$E8),"●","") | L8: =IF(AND(L$5>=$D8,L$5<=$E8),"●","") | M8: =IF(AND(M$5>=$D8,M$5<=$E8),"●","") | N8: =IF(AND(N$5>=$D8,N$5<=$E8),"●","") | O8: =IF(AND(O$5>=$D8,O$5<=$E8),"●","") | ... S8: =IF(AND(S$5>=$D8,S$5<=$E8),"●","")
A9: Planning | B9: Material selections and delivery dates confirmed | C9: Materials Lead | D9: 2 | E9: 3 | F9: 7 | G9: At Risk | H9: =IF(AND(H$5>=$D9,H$5<=$E9),"●","") | I9: =IF(AND(I$5>=$D9,I$5<=$E9),"●","") -> ● | J9: =IF(AND(J$5>=$D9,J$5<=$E9),"●","") -> ● | K9: =IF(AND(K$5>=$D9,K$5<=$E9),"●","") | L9: =IF(AND(L$5>=$D9,L$5<=$E9),"●","") | M9: =IF(AND(M$5>=$D9,M$5<=$E9),"●","") | N9: =IF(AND(N$5>=$D9,N$5<=$E9),"●","") | O9: =IF(AND(O$5>=$D9,O$5<=$E9),"●","") | ... S9: =IF(AND(S$5>=$D9,S$5<=$E9),"●","")
A10: Planning | B10: Trade sequence and site access plan confirmed | C10: Reconstruction Lead | D10: 2 | E10: 3 | F10: 6 | G10: Complete | H10: =IF(AND(H$5>=$D10,H$5<=$E10),"●","") | I10: =IF(AND(I$5>=$D10,I$5<=$E10),"●","") -> ● | J10: =IF(AND(J$5>=$D10,J$5<=$E10),"●","") -> ● | K10: =IF(AND(K$5>=$D10,K$5<=$E10),"●","") | L10: =IF(AND(L$5>=$D10,L$5<=$E10),"●","") | M10: =IF(AND(M$5>=$D10,M$5<=$E10),"●","") | N10: =IF(AND(N$5>=$D10,N$5<=$E10),"●","") | O10: =IF(AND(O$5>=$D10,O$5<=$E10),"●","") | ... S10: =IF(AND(S$5>=$D10,S$5<=$E10),"●","")
A11: Execution | B11: Demo, dry-out verification, plumbing, and structural repairs | C11: Restoration Lead | D11: 3 | E11: 6 | F11: 18 | G11: In Progress | H11: =IF(AND(H$5>=$D11,H$5<=$E11),"●","") | I11: =IF(AND(I$5>=$D11,I$5<=$E11),"●","") | J11: =IF(AND(J$5>=$D11,J$5<=$E11),"●","") -> ● | K11: =IF(AND(K$5>=$D11,K$5<=$E11),"●","") -> ● | L11: =IF(AND(L$5>=$D11,L$5<=$E11),"●","") -> ● | M11: =IF(AND(M$5>=$D11,M$5<=$E11),"●","") -> ● | N11: =IF(AND(N$5>=$D11,N$5<=$E11),"●","") | O11: =IF(AND(O$5>=$D11,O$5<=$E11),"●","") | ... S11: =IF(AND(S$5>=$D11,S$5<=$E11),"●","")
A12: Execution | B12: Electrical, plumbing, and inspection signoffs complete | C12: Trade Leads | D12: 4 | E12: 6 | F12: 12 | G12: At Risk | H12: =IF(AND(H$5>=$D12,H$5<=$E12),"●","") | I12: =IF(AND(I$5>=$D12,I$5<=$E12),"●","") | J12: =IF(AND(J$5>=$D12,J$5<=$E12),"●","") | K12: =IF(AND(K$5>=$D12,K$5<=$E12),"●","") -> ● | L12: =IF(AND(L$5>=$D12,L$5<=$E12),"●","") -> ● | M12: =IF(AND(M$5>=$D12,M$5<=$E12),"●","") -> ● | N12: =IF(AND(N$5>=$D12,N$5<=$E12),"●","") | O12: =IF(AND(O$5>=$D12,O$5<=$E12),"●","") | ... S12: =IF(AND(S$5>=$D12,S$5<=$E12),"●","")
A13: Execution | B13: Drywall, texture, paint, and ceiling repairs | C13: Finish Lead | D13: 6 | E13: 8 | F13: 14 | G13: In Progress | H13: =IF(AND(H$5>=$D13,H$5<=$E13),"●","") | I13: =IF(AND(I$5>=$D13,I$5<=$E13),"●","") | J13: =IF(AND(J$5>=$D13,J$5<=$E13),"●","") | K13: =IF(AND(K$5>=$D13,K$5<=$E13),"●","") | L13: =IF(AND(L$5>=$D13,L$5<=$E13),"●","") | M13: =IF(AND(M$5>=$D13,M$5<=$E13),"●","") -> ● | N13: =IF(AND(N$5>=$D13,N$5<=$E13),"●","") -> ● | O13: =IF(AND(O$5>=$D13,O$5<=$E13),"●","") -> ● | ... S13: =IF(AND(S$5>=$D13,S$5<=$E13),"●","")
A14: Integration | B14: Cabinets, trim, and finish carpentry complete | C14: Finish Lead | D14: 8 | E14: 10 | F14: 15 | G14: Not Started | H14: =IF(AND(H$5>=$D14,H$5<=$E14),"●","") | I14: =IF(AND(I$5>=$D14,I$5<=$E14),"●","") | J14: =IF(AND(J$5>=$D14,J$5<=$E14),"●","") | K14: =IF(AND(K$5>=$D14,K$5<=$E14),"●","") | L14: =IF(AND(L$5>=$D14,L$5<=$E14),"●","") | M14: =IF(AND(M$5>=$D14,M$5<=$E14),"●","") | N14: =IF(AND(N$5>=$D14,N$5<=$E14),"●","") | O14: =IF(AND(O$5>=$D14,O$5<=$E14),"●","") -> ● | ... S14: =IF(AND(S$5>=$D14,S$5<=$E14),"●","")
A15: Integration | B15: Flooring, fixtures, and appliances complete | C15: Finish Lead | D15: 9 | E15: 10 | F15: 10 | G15: Not Started | H15: =IF(AND(H$5>=$D15,H$5<=$E15),"●","") | I15: =IF(AND(I$5>=$D15,I$5<=$E15),"●","") | J15: =IF(AND(J$5>=$D15,J$5<=$E15),"●","") | K15: =IF(AND(K$5>=$D15,K$5<=$E15),"●","") | L15: =IF(AND(L$5>=$D15,L$5<=$E15),"●","") | M15: =IF(AND(M$5>=$D15,M$5<=$E15),"●","") | N15: =IF(AND(N$5>=$D15,N$5<=$E15),"●","") | O15: =IF(AND(O$5>=$D15,O$5<=$E15),"●","") | ... S15: =IF(AND(S$5>=$D15,S$5<=$E15),"●","")
A16: Quality | B16: Room-by-room quality walkthrough and punch list | C16: Project Coordinator | D16: 10 | E16: 11 | F16: 5 | G16: Not Started | H16: =IF(AND(H$5>=$D16,H$5<=$E16),"●","") | I16: =IF(AND(I$5>=$D16,I$5<=$E16),"●","") | J16: =IF(AND(J$5>=$D16,J$5<=$E16),"●","") | K16: =IF(AND(K$5>=$D16,K$5<=$E16),"●","") | L16: =IF(AND(L$5>=$D16,L$5<=$E16),"●","") | M16: =IF(AND(M$5>=$D16,M$5<=$E16),"●","") | N16: =IF(AND(N$5>=$D16,N$5<=$E16),"●","") | O16: =IF(AND(O$5>=$D16,O$5<=$E16),"●","") | ... S16: =IF(AND(S$5>=$D16,S$5<=$E16),"●","")
A17: Quality | B17: Punch list closed and final cleaning complete | C17: Restoration Lead | D17: 11 | E17: 11 | F17: 5 | G17: Not Started | H17: =IF(AND(H$5>=$D17,H$5<=$E17),"●","") | I17: =IF(AND(I$5>=$D17,I$5<=$E17),"●","") | J17: =IF(AND(J$5>=$D17,J$5<=$E17),"●","") | K17: =IF(AND(K$5>=$D17,K$5<=$E17),"●","") | L17: =IF(AND(L$5>=$D17,L$5<=$E17),"●","") | M17: =IF(AND(M$5>=$D17,M$5<=$E17),"●","") | N17: =IF(AND(N$5>=$D17,N$5<=$E17),"●","") | O17: =IF(AND(O$5>=$D17,O$5<=$E17),"●","") | ... S17: =IF(AND(S$5>=$D17,S$5<=$E17),"●","")
... A20: Closeout | B20: Lessons learned and project archive complete | C20: Project Coordinator | D20: 12 | E20: 12 | F20: 3 | G20: Not Started | H20: =IF(AND(H$5>=$D20,H$5<=$E20),"●","") | I20: =IF(AND(I$5>=$D20,I$5<=$E20),"●","") | J20: =IF(AND(J$5>=$D20,J$5<=$E20),"●","") | K20: =IF(AND(K$5>=$D20,K$5<=$E20),"●","") | L20: =IF(AND(L$5>=$D20,L$5<=$E20),"●","") | M20: =IF(AND(M$5>=$D20,M$5<=$E20),"●","") | N20: =IF(AND(N$5>=$D20,N$5<=$E20),"●","") | O20: =IF(AND(O$5>=$D20,O$5<=$E20),"●","") | ... S20: =IF(AND(S$5>=$D20,S$5<=$E20),"●","") -> ●
A21: Flowshua Projects | Clearer projects. Stronger follow-through.

Sheet Budget & Forecast
A1: Budget & Forecast
A2: Illustrative rebuild budget with baseline, actual and committed, and forecast values
A5: Baseline Budget | C5: Actual / Committed | E5: Forecast at Completion | G5: Forecast Variance | I5: Budget Status
A6: =SUM(B11:B16) -> 175000 | C6: =SUM(C11:C16) -> 66000 | E6: =SUM(D11:D16) -> 179000 | G6: =SUM(E11:E16) -> -4000 | I6: =IF(E18>=0,"On Track","At Risk") -> At Risk
A7: Approved fictional rebuild budget | C7: Costs recognized and committed to date | E7: Current projected rebuild spend | G7: Remaining budget protection | I7: Forecast compared to baseline
A10: Category | B10: Baseline Budget | C10: Actual / Committed | D10: Forecast at Completion | E10: Forecast Variance | F10: Status
A11: Emergency mitigation and water cleanup | B11: 26000 | C11: 26000 | D11: 26000 | E11: =B11-D11 -> 0 | F11: Complete
A12: Demo, drying verification, and structural repairs | B12: 22000 | C12: 14000 | D12: 24000 | E12: =B12-D12 -> -2000 | F12: In Progress
A13: Plumbing, electrical, and inspection work | B13: 30000 | C13: 18000 | D13: 34000 | E13: =B13-D13 -> -4000 | F13: At Risk
A14: Drywall, paint, and ceiling repairs | B14: 31000 | C14: 5000 | D14: 31000 | E14: =B14-D14 -> 0 | F14: In Progress
A15: Flooring, cabinets, trim, and finish work | B15: 48000 | C15: 3000 | D15: 52000 | E15: =B15-D15 -> -4000 | F15: At Risk
A16: Contingency reserve | B16: 18000 | C16: 0 | D16: 12000 | E16: =B16-D16 -> 6000 | F16: On Track
A18: Total | B18: =SUM(B11:B16) -> 175000 | C18: =SUM(C11:C16) -> 66000 | D18: =SUM(D11:D16) -> 179000 | E18: =SUM(E11:E16) -> -4000
A41: Flowshua Projects | Clearer projects. Stronger follow-through.

Sheet Procurement & Dependencies
A1: Materials & Dependency Tracker
A2: Fictional material, vendor, inspection, and project-dependency control view
A5: Request ID | B5: Package / Need | C5: Category | D5: Source Strategy | E5: Criticality | F5: Request Week | G5: Forecast Arrival | H5: Linked Work Package | I5: Schedule Impact | J5: Owner | K5: Control Action | L5: Status
A6: PR-001 | B6: Moisture testing and containment supplies | C6: Mitigation support | D6: Local restoration supply | E6: Low | F6: Week 1 | G6: Available now | H6: WP-001 | I6: Low | J6: Restoration Lead | K6: Confirm moisture records are complete before rebuild starts. | L6: Available
A7: PR-002 | B7: Cabinet replacement | C7: Finish material | D7: Approved cabinet vendor | E7: High | F7: Week 2 | G7: Week 7 | H7: WP-009 | I7: High | J7: Project Lead | K7: Confirm homeowner selection and written lead time. | L7: In Review
A8: PR-003 | B8: Matching flooring material | C8: Finish material | D8: Approved flooring vendor | E8: Critical | F8: Week 2 | G8: Forecast pending | H8: WP-010 | I8: Critical | J8: Project Lead | K8: Confirm in-stock options and delivery date before the schedule is locked. | L8: At Risk
A9: PR-004 | B9: Plumbing repair materials | C9: Trade materials | D9: Licensed plumber | E9: Medium | F9: Week 2 | G9: Week 3 | H9: WP-006 | I9: Medium | J9: Reconstruction Lead | K9: Check material list before repair starts. | L9: Confirmed
A10: PR-005 | B10: Electrical fixtures and replacement parts | C10: Trade materials | D10: Licensed electrician | E10: Medium | F10: Week 3 | G10: Week 4 | H10: WP-007 | I10: Medium | J10: Trade Lead | K10: Confirm inspection date and any needed replacement parts. | L10: In Review
A11: PR-006 | B11: Drywall, insulation, and ceiling materials | C11: Finish materials | D11: Local supplier | E11: High | F11: Week 5 | G11: Week 6 | H11: WP-008 | I11: High | J11: Reconstruction Lead | K11: Stage materials before drywall work begins. | L11: In Review
A12: PR-007 | B12: Paint and trim materials | C12: Finish materials | D12: Local supplier | E12: Low | F12: Week 7 | G12: Week 8 | H12: WP-008 | I12: Low | J12: Finish Lead | K12: Confirm color and delivery before paint starts. | L12: Available
A13: PR-008 | B13: Warranty and closeout paperwork | C13: Project records | D13: Project controls | E13: Medium | F13: Week 10 | G13: Week 12 | H13: WP-013 | I13: Medium | J13: Project Coordinator | K13: Build the final packet before the homeowner walkthrough. | L13: Not Started
A14: Flowshua Projects | Clearer projects. Stronger follow-through.

Sheet Quality Gates
A1: Quality Gates & Homeowner Walkthrough Checklist
A2: Fictional approval, inspection, and final walkthrough conditions before homeowner acceptance
A5: Gate ID | B5: Phase | C5: Quality / Decision Gate | D5: Required Evidence | E5: Owner | F5: Planned Week | G5: Status | H5: Schedule Impact | I5: Control Action | J5: Acceptance Condition
A6: G-001 | B6: Planning | C6: Initial damage scope and homeowner priorities approved | D6: Damage photos, scope notes, and owner decisions | E6: Homeowner / Project Lead | F6: 2 | G6: Complete | H6: Low | I6: Keep scope changes visible. | J6: Rebuild goal and approved work are understood.
A7: G-002 | B7: Planning | C7: Cabinet and flooring plan confirmed | D7: Selections, vendor dates, and ordering plan | E7: Project Lead / Homeowner | F7: 3 | G7: At Risk | H7: High | I7: Get written selections and backup options. | J7: Materials have a reliable arrival date.
A8: G-003 | B8: Execution | C8: Plumbing, electrical, and rough-in work complete | D8: Trade signoff and inspection evidence | E8: Reconstruction Lead | F8: 6 | G8: In Progress | H8: Medium | I8: Protect inspection window and trade handoffs. | J8: Walls are ready to close and no open trade issue remains.
A9: G-004 | B9: Execution | C9: Drywall and paint phase complete | D9: Quality check and room photos | E9: Finish Lead | F9: 8 | G9: In Progress | H9: Medium | I9: Check finish before cabinets and flooring. | J9: Repaired areas match surrounding space.
A10: G-005 | B10: Integration | C10: Cabinets, trim, flooring, and fixture work complete | D10: Vendor completion notes and room review | E10: Project Lead | F10: 10 | G10: Not Started | H10: High | I10: Confirm material dates and site access. | J10: Finish work is complete enough for final walk.
A11: G-006 | B11: Quality | C11: Final quality walkthrough and punch list closure | D11: Room-by-room list and closed items | E11: Project Lead / Homeowner | F11: 11 | G11: Not Started | H11: High | I11: Use a room-by-room closeout list. | J11: No open issue blocks homeowner return.
A12: G-007 | B12: Readiness | C12: Homeowner acceptance and closeout packet complete | D12: Signed walkthrough, warranty files, and final project summary | E12: Homeowner / Project Lead | F12: 12 | G12: Not Started | H12: Critical | I12: Align final walk and closeout file. | J12: Homeowner accepts the project and records are complete.
A13: Flowshua Projects | Clearer projects. Stronger follow-through.

Sheet RAIDD
A1: RAIDD Log
A2: Risks, assumptions, issues, decisions, and dependencies that need a clear owner
A5: ID | B5: Type | C5: Description | D5: Owner | E5: Impact | F5: Priority | G5: Due Week | H5: Status | I5: Response / Next Action
A6: R-01 | B6: Risk | C6: Cabinet delivery may miss the installation window. | D6: Project Lead | E6: Could delay trim, flooring, and final walkthrough. | F6: High | G6: Week 3 | H6: Open | I6: Confirm lead time and a backup option.
A7: R-02 | B7: Risk | C7: Hidden damage may show up when walls or flooring are opened. | D7: Restoration Lead | E7: Could grow scope, cost, and schedule. | F7: High | G7: Week 4 | H7: Open | I7: Document finding, price change, and get approval before work continues.
A8: R-03 | B8: Risk | C8: Flooring material may not match or arrive in time. | D8: Materials Lead | E8: Could delay finish work and closeout. | F8: Critical | G8: Week 3 | H8: At Risk | I8: Confirm available options and delivery date.
A9: A-01 | B9: Assumption | C9: Mitigation work and moisture records are complete enough to start rebuild work. | D9: Restoration Lead | E9: Schedule holds if drying information is incomplete. | F9: Medium | G9: Week 2 | H9: Open | I9: Check final moisture record before demo.
A10: A-02 | B10: Assumption | C10: Homeowner can make finish choices inside the agreed decision window. | D10: Homeowner | E10: Late choices can delay materials and trade booking. | F10: High | G10: Week 3 | H10: Open | I10: Send a short decision list with clear deadlines.
A11: I-01 | B11: Issue | C11: Adjuster decision on concealed moisture scope is not back yet. | D11: Project Lead | E11: Demolition and drywall scope are exposed. | F11: Critical | G11: Week 2 | H11: At Risk | I11: Submit photos and estimate. Follow up until there is written direction.
A12: I-02 | B12: Issue | C12: Electrical vendor has not confirmed an inspection slot. | D12: Trade Lead | E12: Could delay wall close-up and drywall start. | F12: High | G12: Week 4 | H12: Open | I12: Confirm appointment or line up a backup.
A13: D-01 | B13: Decision | C13: Use one shared rebuild schedule and project tracker instead of managing through texts alone. | D13: Project Lead | E13: Owner and vendors see the same priorities and next steps. | F13: High | G13: Week 1 | H13: Approved | I13: Update the tracker weekly and after major changes.
A14: D-02 | B14: Decision | C14: Keep cabinet and flooring deadlines firm and use approved backup options if lead time slips. | D14: Project Lead / Homeowner | E14: Protects the finish schedule. | F14: High | G14: Week 3 | H14: Approved | I14: Confirm choices and approve alternates.
A15: D-03 | B15: Dependency | C15: Final owner walkthrough depends on punch-list closure, warranty packet, final clean, and all trades closing their work. | D15: Project Lead | E15: Defines the Week 12 acceptance condition. | F15: Critical | G15: Week 12 | H15: Open | I15: Track as one linked closeout gate.
A16: Flowshua Projects | Clearer projects. Stronger follow-through.

Sheet Lessons Learned
A1: Closeout & Lessons Learned
A2: Capture what worked and what needs to be better before the project closes
A5: Lessons Captured to Date
A6: Lesson ID | B6: Project Moment | C6: What Happened | D6: Lesson | E6: Recommended Standard | F6: Owner | G6: Reuse Opportunity | H6: Status
A7: LL-01 | B7: Scope and homeowner decisions | C7: Early photos, room-by-room notes, and approval points make it easier to keep a rebuild from becoming a guessing game. | D7: Get the scope and decision deadlines clear early, then track changes in one place. | E7: Start every rebuild with a short scope summary, homeowner decision list, and change log. | F7: Project Lead | G7: Future restoration and renovation projects | H7: Complete
A8: LL-02 | B8: Materials | C8: One cabinet or flooring delay can impact half the finish schedule. | D8: Long-lead items need active follow-up before finish work starts. | E8: Flag cabinets, flooring, fixtures, and special-order materials as critical dependencies and check dates twice a week. | F8: Materials Lead | G8: Materials and vendor tracker | H8: In Progress
A9: LL-03 | B9: Trade handoffs | C9: Rough-in, inspection, drywall, and finishes are tied together. A missed handoff makes the next trade wait. | D9: Confirm who owns the handoff and what has to be complete before the next step. | E9: Use a short ready-for-next-trade checklist. | F9: Reconstruction Lead | G9: Trade coordination plan | H9: In Progress
A10: LL-04 | B10: Final quality | C10: Waiting until the end to find punch items can turn a final walk into several extra weeks. | D10: Quality checks should happen room by room before the owner walkthrough. | E10: Build the punch list before final clean and warranty handoff. | F10: Project Lead | G10: Quality gate checklist | H10: Not Started
A11: LL-05 | B11: Homeowner updates | C11: A simple weekly update keeps the homeowner from having to chase answers. | D11: Owners need a clear view of what was done, what is next, and what needs a decision. | E11: Use a one-page weekly update during active rebuild work. | F11: Project Lead | G11: Weekly status update | H11: Complete
A14: Project Closeout Checklist
A15: Project Closeout Checklist | B15: Owner | C15: Target Week | D15: Evidence Required | E15: Status | F15: Why It Matters | G15: Follow-up | H15: Portfolio Note
A16: Closeout Item | B16: Owner | C16: Target Week | D16: Evidence Required | E16: Status | F16: Why It Matters | G16: Follow-up | H16: Portfolio Note
A17: Final walkthrough package | B17: Project Lead | C17: Week 12 | D17: Signed walkthrough, room checklist, warranty packet, and final status update | E17: Not Started | F17: Gives the homeowner a clear final handoff. | G17: Build it before the walkthrough. | H17: Fictional case-study artifact
A18: Budget reconciliation | B18: Project Controls | C18: Week 12 | D18: Final forecast, variance explanation, and contingency use | E18: Not Started | F18: Confirms cost control and any scope changes. | G18: Update after vendor invoices are forecast. | H18: Illustrative project cost view
A19: RAIDD closure review | B19: Project Lead | C19: Week 12 | D19: Open item disposition and change archive | E19: Not Started | F19: Makes sure no loose risk is left behind. | G19: Close or transition every item. | H19: Illustrative governance control
A20: Lessons learned review | B20: Homeowner / Project Lead | C20: Week 12 | D20: Approved lessons summary and what to reuse next time | E20: Not Started | F20: Turns the project into better future work. | G20: Review after walkthrough. | H20: Public portfolio-safe summary only
A21: Workbook archive | B21: Project Coordinator | C21: Week 12 | D21: Final workbook and restoration project case-study narrative | E21: Not Started | F21: Keeps the project easy to explain and reuse. | G21: Publish approved portfolio copy. | H21: No real client information included
A22: Flowshua Projects | Clearer projects. Stronger follow-through.
